kgraph/__init__.py
kgraph/kgraph_core.py
kgraph/utils.py
kgraph_ts-0.0.1.dist-info/LICENSE
kgraph_ts-0.0.1.dist-info/METADATA
kgraph_ts-0.0.1.dist-info/WHEEL
kgraph_ts-0.0.1.dist-info/top_level.txt
kgraph_ts-0.0.1.dist-info/zip-safe
kgraph_ts-0.0.1.dist-info/RECORD
