Metadata-Version: 2.1
Name: kgraph-ts
Version: 0.0.1
Summary: kGraph
Home-page: https://github.com/boniolp/kGraph
Author: Paul Boniol
Author-email: paul.boniol@inria.fr
Classifier: Development Status :: 5 - Production/Stable
Classifier: Intended Audience :: Developers
Classifier: License :: OSI Approved :: MIT License
Classifier: Natural Language :: English
Classifier: Operating System :: OS Independent
Classifier: Programming Language :: Python
Classifier: Programming Language :: Python :: 3.9
Classifier: Topic :: Scientific/Engineering :: Information Analysis
Classifier: Topic :: Scientific/Engineering :: Mathematics
Classifier: Topic :: Software Development :: Libraries :: Python Modules
License-File: LICENSE
Requires-Dist: aeon ==0.6.0
Requires-Dist: setuptools >=65.5.1
Requires-Dist: numpy ==1.24.4
Requires-Dist: pandas ==2.0.3
Requires-Dist: matplotlib ==3.7.2
Requires-Dist: scipy ==1.11.3
Requires-Dist: scikit-learn ==1.2.2
Requires-Dist: networkx ==3.1
